alphanetworks/__init__.py
alphanetworks/layers.py
alphanetworks/models.py
alphanetworks/utils.py
scripts/__init__.py
scripts/train_model.py
alphanetworks-0.3.5.dist-info/LICENSE
alphanetworks-0.3.5.dist-info/METADATA
alphanetworks-0.3.5.dist-info/WHEEL
alphanetworks-0.3.5.dist-info/entry_points.txt
alphanetworks-0.3.5.dist-info/top_level.txt
alphanetworks-0.3.5.dist-info/RECORD
