Metadata-Version: 2.1
Name: alphanetworks
Version: 0.3.5
Summary: Custom deep learning layers and hybrid models for image classification.
Home-page: https://github.com/ihtesham-jahangir/alphanetworks
Author: Team AlphaNetworks
Author-email: ihteshamjahangir21@gmail.com.com
Classifier: Programming Language :: Python :: 3
Classifier: License :: OSI Approved :: MIT License
Classifier: Operating System :: OS Independent
Requires-Python: >=3.6
License-File: LICENSE
Requires-Dist: tensorflow>=2.0
Requires-Dist: numpy
Requires-Dist: matplotlib
